Metadata-Version: 1.1
Name: goza
Version: 0.0.9
Summary: You personal Python assistant
Home-page: UNKNOWN
Author: Zach Gongaware
Author-email: UNKNOWN
License: UNKNOWN
Platform: UNKNOWN
Classifier: Programming Language :: Python :: 3
Classifier: License :: OSI Approved :: MIT License
Classifier: Operating System :: OS Independent
